abi2le_mirror_bert_colinglab/__init__.py
abi2le_mirror_bert_colinglab/contrastive_learning.py
abi2le_mirror_bert_colinglab/data_loader.py
abi2le_mirror_bert_colinglab/drophead.py
abi2le_mirror_bert_colinglab/mirror_bert.py
abi2le_mirror_bert_colinglab-0.0.1.dist-info/LICENSE
abi2le_mirror_bert_colinglab-0.0.1.dist-info/METADATA
abi2le_mirror_bert_colinglab-0.0.1.dist-info/WHEEL
abi2le_mirror_bert_colinglab-0.0.1.dist-info/top_level.txt
abi2le_mirror_bert_colinglab-0.0.1.dist-info/RECORD
